html_scrubber/__init__.py
html_scrubber/cleaner.py
html_scrubber-0.0.3.dist-info/LICENSE
html_scrubber-0.0.3.dist-info/METADATA
html_scrubber-0.0.3.dist-info/WHEEL
html_scrubber-0.0.3.dist-info/top_level.txt
html_scrubber-0.0.3.dist-info/RECORD
