Metadata-Version: 2.2
Name: html-scrubber
Version: 0.0.3
Summary: A simple HTML cleaner utility built with BeautifulSoup. This library allows you to easily clean HTML content by removing unwanted tags like styles, scripts, iframes, and more. It provides an easy-to-use interface for cleaning HTML from various sources, making it ideal for web scraping, data extraction, or sanitizing HTML content before processing.
Requires-Python: >=3.12
License-File: LICENSE
Requires-Dist: beautifulsoup4
